{
	"id": "696de88e-bf3c-4346-8f0a-e90b602cebaf",
	"name": "Restful Booker Env",
	"values": [
		{
			"key": "baseUrl",
			"value": "",
			"type": "default",
			"enabled": true
		},
		{
			"key": "bookingId",
			"value": "",
			"type": "any",
			"enabled": true
		},
		{
			"key": "accessToken",
			"value": "",
			"type": "any",
			"enabled": true
		}
	],
	"color": null,
	"_postman_variable_scope": "environment",
	"_postman_exported_at": "2026-02-08T10:47:47.480Z",
	"_postman_exported_using": "Postman/11.83.6-260206-0233"
}